README.txt
setup.py
disk_dict/__init__.py
disk_dict/disk_dict.py
disk_dict.egg-info/PKG-INFO
disk_dict.egg-info/SOURCES.txt
disk_dict.egg-info/dependency_links.txt
disk_dict.egg-info/requires.txt
disk_dict.egg-info/top_level.txt