Metadata-Version: 1.1
Name: disk-dict
Version: 2.2.0
Summary: A disk-based key/value store in Python.
Home-page: https://github.com/AWNystrom/DiskDict
Author: Andrew Nystrom
Author-email: AWNystrom@gmail.com
License: Apache 2.0
Keywords: disk,based,key,value,store,dict,diskdict
Platform: UNKNOWN
Classifier: Programming Language :: Python
Classifier: Programming Language :: Python :: 2.7
Classifier: Programming Language :: Python :: 2
Classifier: License :: OSI Approved :: Apache Software License
Classifier: Operating System :: OS Independent
Classifier: Development Status :: 4 - Beta
Classifier: Intended Audience :: Developers
